osmp/__version__.py
osmp/analyse.py
osmp/encode.py
osmp/eprofile.py
osmp/executor.py
osmp/multiplexer.py
osmp/osmp.py
osmp/package.py
osmp/processor.py
osmp/rendition.py
osmp/transfer.py
osmp/utils.py
opinionated_streaming_media_processor-0.2.0.dist-info/METADATA
opinionated_streaming_media_processor-0.2.0.dist-info/WHEEL
opinionated_streaming_media_processor-0.2.0.dist-info/entry_points.txt
opinionated_streaming_media_processor-0.2.0.dist-info/RECORD
